pyansilove/__init__.py
pyansilove/cli.py
pyansilove/constants.py
pyansilove/font.py
pyansilove/pyansilove.py
pyansilove/schemas.py
pyansilove/utils.py
pyansilove/fonts/__init__.py
pyansilove/fonts/font_amiga_microknight.py
pyansilove/fonts/font_amiga_microknight_plus.py
pyansilove/fonts/font_amiga_mosoul.py
pyansilove/fonts/font_amiga_pot_noodle.py
pyansilove/fonts/font_amiga_topaz_1200.py
pyansilove/fonts/font_amiga_topaz_1200_plus.py
pyansilove/fonts/font_amiga_topaz_500.py
pyansilove/fonts/font_amiga_topaz_500_plus.py
pyansilove/fonts/font_pc_80x25.py
pyansilove/fonts/font_pc_80x50.py
pyansilove/fonts/font_pc_baltic.py
pyansilove/fonts/font_pc_cyrillic.py
pyansilove/fonts/font_pc_french_canadian.py
pyansilove/fonts/font_pc_greek.py
pyansilove/fonts/font_pc_greek869.py
pyansilove/fonts/font_pc_hebrew.py
pyansilove/fonts/font_pc_icelandic.py
pyansilove/fonts/font_pc_latin1.py
pyansilove/fonts/font_pc_latin2.py
pyansilove/fonts/font_pc_nordic.py
pyansilove/fonts/font_pc_portuguese.py
pyansilove/fonts/font_pc_russian.py
pyansilove/fonts/font_pc_spleen.py
pyansilove/fonts/font_pc_terminus.py
pyansilove/fonts/font_pc_turkish.py
pyansilove/loaders/__init__.py
pyansilove/loaders/ansi.py
pyansilove-1.4.1.dist-info/AUTHORS.rst
pyansilove-1.4.1.dist-info/LICENSE
pyansilove-1.4.1.dist-info/METADATA
pyansilove-1.4.1.dist-info/WHEEL
pyansilove-1.4.1.dist-info/entry_points.txt
pyansilove-1.4.1.dist-info/top_level.txt
pyansilove-1.4.1.dist-info/RECORD
