Metadata-Version: 2.1
Name: pyansilove
Version: 1.4.1
Summary: Library for converting ANSI, ASCII, and other formats to PNG
Home-page: https://github.com/BakasuraRCE/pyansilove
Author: Bakasura
Author-email: bakasura@protonmail.ch
License: BSD license
Keywords: pyansilove
Classifier: Development Status :: 2 - Pre-Alpha
Classifier: Intended Audience :: Developers
Classifier: License :: OSI Approved :: BSD License
Classifier: Natural Language :: English
Classifier: Programming Language :: Python :: 3
Classifier: Programming Language :: Python :: 3.6
Classifier: Programming Language :: Python :: 3.7
Classifier: Programming Language :: Python :: 3.8
Classifier: Programming Language :: Python :: 3.9
Classifier: Programming Language :: Python :: 3.10
Classifier: Programming Language :: Python :: 3.11
Requires-Python: >=3.6
License-File: LICENSE
License-File: AUTHORS.rst
Requires-Dist: Click (>=7.0)
Requires-Dist: pydantic (>=1.10)
Requires-Dist: pillow (>=9.5)
